LICENSE.txt
README.md
setup.cfg
setup.py
databricks_mermaid.egg-info/PKG-INFO
databricks_mermaid.egg-info/SOURCES.txt
databricks_mermaid.egg-info/dependency_links.txt
databricks_mermaid.egg-info/requires.txt
databricks_mermaid.egg-info/top_level.txt
src/DatabricksMermaidCellMagic.py
src/__init__.py