Metadata-Version: 2.1
Name: databricks-mermaid
Version: 0.1
Summary: Cell magic to allow for usage of mermaid notation inside Databricks
Home-page: https://github.com/sgmarius/databricks-mermaid
Author: Marius Sandu
Author-email: marius@ltng-bi.com
License: MIT
Download-URL: https://github.com/sgmarius/databricks-mermaid/blob/main/dist/databricks-mermaid-0.1.tar.gz
Keywords: Databricks,Mermaid
Platform: UNKNOWN
Classifier: Development Status :: 3 - Alpha
Classifier: Intended Audience :: Developers
Classifier: Topic :: Software Development :: Build Tools
Classifier: License :: OSI Approved :: MIT License
Classifier: Programming Language :: Python :: 3
Classifier: Programming Language :: Python :: 3.4
Classifier: Programming Language :: Python :: 3.5
Classifier: Programming Language :: Python :: 3.6
License-File: LICENSE.txt
